README.md
pyproject.toml
setup.cfg
setup.py
src/causalimpact/__init__.py
src/causalimpact/analysis.py
src/causalimpact/inferences.py
src/causalimpact/misc.py
src/causalimpact/model.py
src/causalimpactreturn.egg-info/PKG-INFO
src/causalimpactreturn.egg-info/SOURCES.txt
src/causalimpactreturn.egg-info/dependency_links.txt
src/causalimpactreturn.egg-info/not-zip-safe
src/causalimpactreturn.egg-info/requires.txt
src/causalimpactreturn.egg-info/top_level.txt
tests/test_analysis.py
tests/test_inferences.py
tests/test_misc.py
tests/test_model.py