Metadata-Version: 2.1
Name: causalimpactreturn
Version: 1.0.0
Summary: Python Package for causal inference using Bayesian structural time-series models
Home-page: https://github.com/danwdigital/causalimpactreturn
Author: Jamal Senouci
Author-email: jamalsenouci@gmail.com
License: MIT
Platform: any
Classifier: Development Status :: 4 - Beta
Classifier: Programming Language :: Python
Requires-Python: >=2.6
Requires-Dist: pandas
Requires-Dist: numpy
Requires-Dist: statsmodels
Requires-Dist: matplotlib
Requires-Dist: pymc
Requires-Dist: pytensor
Requires-Dist: importlib-metadata; python_version < "3.8"
Provides-Extra: testing
Requires-Dist: setuptools; extra == "testing"
Requires-Dist: pytest; extra == "testing"
Requires-Dist: pytest-cov; extra == "testing"
